{
  "_class": "shapePath",
  "booleanOperation": -1,
  "do_objectID": "613FDDBF-E4B6-4091-A786-6CD00AB0C486",
  "edited": true,
  "exportOptions": {
    "_class": "exportOptions",
    "do_objectID": "0AAAB556-99DC-4CD5-823B-5B4C48AA3836",
    "exportFormats": [
    ],
    "includedLayerIds": [
    ],
    "layerOptions": 0,
    "shouldTrim": false
  },
  "frame": {
    "_class": "rect",
    "constrainProportions": false,
    "do_objectID": "4D3CE461-A3F2-4C00-BB67-9EDBE311F8FF",
    "height": 2.989285714285714,
    "width": 2.989285714285713,
    "x": 23.30757142857143,
    "y": 7.971428571428572
  },
  "isClosed": true,
  "isFlippedHorizontal": false,
  "isFlippedVertical": false,
  "isLocked": false,
  "isVisible": true,
  "layerListExpandedType": 0,
  "name": "Path",
  "nameIsFixed": false,
  "pointRadiusBehaviour": 0,
  "points": [
    {
      "_class": "curvePoint",
      "cornerRadius": 0,
      "curveFrom": "{1, 0.77629629629629648}",
      "curveMode": 4,
      "curveTo": "{1, 0.50000000000000067}",
      "hasCurveFrom": true,
      "hasCurveTo": false,
      "point": "{1, 0.50000000000000067}"
    },
    {
      "_class": "curvePoint",
      "cornerRadius": 0,
      "curveFrom": "{0.22444444444444381, 1}",
      "curveMode": 2,
      "curveTo": "{0.77629629629629648, 1}",
      "hasCurveFrom": true,
      "hasCurveTo": true,
      "point": "{0.50074074074074104, 1}"
    },
    {
      "_class": "curvePoint",
      "cornerRadius": 0,
      "curveFrom": "{0, 0.22370370370370346}",
      "curveMode": 2,
      "curveTo": "{0, 0.77629629629629648}",
      "hasCurveFrom": true,
      "hasCurveTo": true,
      "point": "{0, 0.50000000000000067}"
    },
    {
      "_class": "curvePoint",
      "cornerRadius": 0,
      "curveFrom": "{0.77629629629629648, 0}",
      "curveMode": 2,
      "curveTo": "{0.22444444444444381, 0}",
      "hasCurveFrom": true,
      "hasCurveTo": true,
      "point": "{0.50074074074074104, 0}"
    },
    {
      "_class": "curvePoint",
      "cornerRadius": 0,
      "curveFrom": "{1, 0.50000000000000067}",
      "curveMode": 4,
      "curveTo": "{1, 0.22370370370370346}",
      "hasCurveFrom": false,
      "hasCurveTo": true,
      "point": "{1, 0.50000000000000067}"
    }
  ],
  "resizingConstraint": 63,
  "resizingType": 0,
  "rotation": 0,
  "shouldBreakMaskChain": false
}