{
  "_class": "shapePath",
  "booleanOperation": -1,
  "do_objectID": "58369670-03D5-4064-A059-54F88DCCB7B8",
  "edited": true,
  "exportOptions": {
    "_class": "exportOptions",
    "exportFormats": [
    ],
    "includedLayerIds": [
    ],
    "layerOptions": 0,
    "shouldTrim": false
  },
  "frame": {
    "_class": "rect",
    "constrainProportions": false,
    "height": 12.09211282788358,
    "width": 12.09211282788358,
    "x": 0,
    "y": 0
  },
  "isClosed": false,
  "isFlippedHorizontal": false,
  "isFlippedVertical": false,
  "isLocked": false,
  "isVisible": true,
  "layerListExpandedType": 0,
  "name": "Path",
  "nameIsFixed": false,
  "pointRadiusBehaviour": 0,
  "points": [
    {
      "_class": "curvePoint",
      "cornerRadius": 0,
      "curveFrom": "{0.22377358490566035, 0}",
      "curveMode": 4,
      "curveTo": "{0.49999999999999994, 0}",
      "hasCurveFrom": true,
      "hasCurveTo": false,
      "point": "{0.49999999999999994, 0}"
    },
    {
      "_class": "curvePoint",
      "cornerRadius": 0,
      "curveFrom": "{0, 0.77622641509433965}",
      "curveMode": 2,
      "curveTo": "{0, 0.22389937106918212}",
      "hasCurveFrom": true,
      "hasCurveTo": true,
      "point": "{0, 0.49999999999999978}"
    },
    {
      "_class": "curvePoint",
      "cornerRadius": 0,
      "curveFrom": "{0.77610062893081755, 1}",
      "curveMode": 2,
      "curveTo": "{0.22377358490566035, 1}",
      "hasCurveFrom": true,
      "hasCurveTo": true,
      "point": "{0.49999999999999994, 1}"
    },
    {
      "_class": "curvePoint",
      "cornerRadius": 0,
      "curveFrom": "{1, 0.22389937106918212}",
      "curveMode": 2,
      "curveTo": "{1, 0.77622641509433965}",
      "hasCurveFrom": true,
      "hasCurveTo": true,
      "point": "{1, 0.49999999999999978}"
    },
    {
      "_class": "curvePoint",
      "cornerRadius": 0,
      "curveFrom": "{0.49999999999999994, 0}",
      "curveMode": 4,
      "curveTo": "{0.77610062893081755, 0}",
      "hasCurveFrom": false,
      "hasCurveTo": true,
      "point": "{0.49999999999999994, 0}"
    }
  ],
  "resizingConstraint": 63,
  "resizingType": 0,
  "rotation": 0,
  "shouldBreakMaskChain": false
}