{
  "_class": "shapeGroup",
  "clippingMaskMode": 0,
  "do_objectID": "B1538608-70A0-4419-8A22-930E7018B6E5",
  "exportOptions": {
    "_class": "exportOptions",
    "do_objectID": "98A8F05F-311B-48FC-976C-06597910F7CC",
    "exportFormats": [
    ],
    "includedLayerIds": [
    ],
    "layerOptions": 0,
    "shouldTrim": false
  },
  "frame": {
    "_class": "rect",
    "constrainProportions": false,
    "do_objectID": "753078EB-0EAA-4B9D-98DB-9B8360CF8CC0",
    "height": 12,
    "width": 18,
    "x": 19,
    "y": 46
  },
  "hasClickThrough": false,
  "hasClippingMask": false,
  "isFlippedHorizontal": false,
  "isFlippedVertical": false,
  "isLocked": false,
  "isVisible": true,
  "layerListExpandedType": 1,
  "layers": [
    {
      "class": "rectangle",
      "id": "4D2478EB-0005-4675-B4AE-51E1AA9560BC"
    },
    {
      "class": "rectangle",
      "id": "7ABBC73B-9126-424D-97C0-5CC5690A5B16"
    },
    {
      "class": "rectangle",
      "id": "C2AA45AA-4CFE-4238-8D33-2E5121A94BCF"
    }
  ],
  "name": "ic_menu",
  "nameIsFixed": true,
  "resizingConstraint": 63,
  "resizingType": 0,
  "rotation": 0,
  "shouldBreakMaskChain": false,
  "style": {
    "_class": "style",
    "borders": [
      {
        "_class": "border",
        "color": {
          "_class": "color",
          "alpha": 1,
          "blue": 0.592,
          "green": 0.592,
          "red": 0.592
        },
        "fillType": 0,
        "isEnabled": false,
        "position": 1,
        "thickness": 1
      }
    ],
    "do_objectID": "BDA1E889-FED3-45DD-A588-747456EA1658",
    "endDecorationType": 0,
    "fills": [
      {
        "_class": "fill",
        "color": {
          "_class": "color",
          "alpha": 1,
          "blue": 1,
          "green": 1,
          "red": 1
        },
        "fillType": 0,
        "isEnabled": true,
        "noiseIndex": 0,
        "noiseIntensity": 0,
        "patternFillType": 0,
        "patternTileScale": 1
      }
    ],
    "miterLimit": 10,
    "startDecorationType": 0
  },
  "windingRule": 1
}