{
  "_class": "shapePath",
  "booleanOperation": -1,
  "do_objectID": "F6C7047B-E8E6-48E4-99A3-9D8A5C8F3FE1",
  "edited": true,
  "exportOptions": {
    "_class": "exportOptions",
    "exportFormats": [
    ],
    "includedLayerIds": [
    ],
    "layerOptions": 0,
    "shouldTrim": false
  },
  "frame": {
    "_class": "rect",
    "constrainProportions": false,
    "height": 2,
    "width": 69.99999999999999,
    "x": 0,
    "y": 0
  },
  "isClosed": false,
  "isFlippedHorizontal": false,
  "isFlippedVertical": false,
  "isLocked": false,
  "isVisible": true,
  "layerListExpandedType": 0,
  "name": "Path",
  "nameIsFixed": false,
  "pointRadiusBehaviour": 0,
  "points": [
    {
      "_class": "curvePoint",
      "cornerRadius": 0,
      "curveFrom": "{0.0023809523809523803, 1}",
      "curveMode": 1,
      "curveTo": "{0.0023809523809523803, 1}",
      "do_objectID": "E89E438C-6D25-4F6E-8F81-32892D8FAD19",
      "hasCurveFrom": false,
      "hasCurveTo": false,
      "point": "{0, 0.5}"
    },
    {
      "_class": "curvePoint",
      "cornerRadius": 0,
      "curveFrom": "{0.0071428571428571426, 2}",
      "curveMode": 1,
      "curveTo": "{0.0071428571428571426, 2}",
      "do_objectID": "260EE366-B400-4FA5-BCD7-B0BD3B194C84",
      "hasCurveFrom": false,
      "hasCurveTo": false,
      "point": "{1, 0.5}"
    }
  ],
  "resizingConstraint": 63,
  "resizingType": 0,
  "rotation": 0,
  "shouldBreakMaskChain": false
}