{
  "_class": "shapeGroup",
  "clippingMaskMode": 0,
  "do_objectID": "41AFB62D-B445-426E-A3C0-98BE710A0C05",
  "exportOptions": {
    "_class": "exportOptions",
    "do_objectID": "BFBBC126-4BC5-403A-B168-2F4ED6C68A67",
    "exportFormats": [
    ],
    "includedLayerIds": [
    ],
    "layerOptions": 0,
    "shouldTrim": false
  },
  "frame": {
    "_class": "rect",
    "constrainProportions": false,
    "do_objectID": "B8A250B5-E81D-46DC-8E61-796E9281EDAA",
    "height": 114.0151515151515,
    "width": 114.0151515151515,
    "x": 0,
    "y": 0.9924242424242493
  },
  "hasClickThrough": false,
  "hasClippingMask": true,
  "isFlippedHorizontal": false,
  "isFlippedVertical": false,
  "isLocked": false,
  "isVisible": true,
  "layerListExpandedType": 1,
  "layers": [
    {
      "class": "rectangle",
      "id": "DCF629AF-2C03-42C2-ABB3-ECBBB5EC0F48"
    }
  ],
  "name": "card",
  "nameIsFixed": false,
  "resizingConstraint": 63,
  "resizingType": 0,
  "rotation": 0,
  "shouldBreakMaskChain": false,
  "style": {
    "_class": "style",
    "do_objectID": "DF711983-AE52-4F65-9C1D-9CAA61E97F57",
    "endDecorationType": 0,
    "fills": [
      {
        "_class": "fill",
        "color": {
          "_class": "color",
          "alpha": 1,
          "blue": 0.03921568627450975,
          "green": 0.8,
          "red": 0.6235294117647059
        },
        "fillType": 0,
        "isEnabled": true,
        "noiseIndex": 0,
        "noiseIntensity": 0,
        "patternFillType": 0,
        "patternTileScale": 1
      }
    ],
    "miterLimit": 10,
    "sharedObjectID": "A41A5B3E-1B0B-4FEC-B442-F5963CDD786A",
    "startDecorationType": 0
  },
  "windingRule": 1
}