{
  "_class": "shapePath",
  "booleanOperation": -1,
  "do_objectID": "E355AE90-B8CC-4897-BC27-65E61D7532DC",
  "edited": true,
  "exportOptions": {
    "_class": "exportOptions",
    "exportFormats": [
    ],
    "includedLayerIds": [
    ],
    "layerOptions": 0,
    "shouldTrim": false
  },
  "frame": {
    "_class": "rect",
    "constrainProportions": false,
    "height": 2,
    "width": 69.99999999999999,
    "x": 0,
    "y": 0
  },
  "isClosed": false,
  "isFlippedHorizontal": false,
  "isFlippedVertical": false,
  "isLocked": false,
  "isVisible": true,
  "layerListExpandedType": 0,
  "name": "Path",
  "nameIsFixed": false,
  "pointRadiusBehaviour": 0,
  "points": [
    {
      "_class": "curvePoint",
      "cornerRadius": 0,
      "curveFrom": "{0.0023809523809523803, 1}",
      "curveMode": 1,
      "curveTo": "{0.0023809523809523803, 1}",
      "do_objectID": "F4F08C41-558B-476B-8916-3A41FF5D15D2",
      "hasCurveFrom": false,
      "hasCurveTo": false,
      "point": "{0, 0.5}"
    },
    {
      "_class": "curvePoint",
      "cornerRadius": 0,
      "curveFrom": "{0.0071428571428571426, 2}",
      "curveMode": 1,
      "curveTo": "{0.0071428571428571426, 2}",
      "do_objectID": "834CE250-EDDE-4757-8DF8-DDB1ED693F6A",
      "hasCurveFrom": false,
      "hasCurveTo": false,
      "point": "{1, 0.5}"
    }
  ],
  "resizingConstraint": 63,
  "resizingType": 0,
  "rotation": 0,
  "shouldBreakMaskChain": false
}